pyproject.toml
mywatering/__init__.py
mywatering/__main__.py
mywatering/cli.py
mywatering/common.py
mywatering/temperature.py
mywatering/watering.py
mywatering_client-0.2.6.dist-info/METADATA
mywatering_client-0.2.6.dist-info/WHEEL
mywatering_client-0.2.6.dist-info/entry_points.txt
mywatering_client-0.2.6.dist-info/licenses/LICENSE
mywatering_client-0.2.6.dist-info/RECORD
