Metadata-Version: 2.4
Name: mywatering-client
Version: 0.2.6
Summary: MyWatering client
Project-URL: Homepage, https://codeberg.org/mywatering/mywatering-client
Project-URL: Repository, https://codeberg.org/mywatering/mywatering-client
Project-URL: Issues, https://codeberg.org/mywatering/mywatering-client/issues
Author-email: Jaroslav Beran <jaroslav.beran@gmail.com>
License-Expression: GPL-3.0
License-File: LICENSE
Requires-Python: >=3.11
Requires-Dist: adafruit-circuitpython-dht>=4.0.7
Requires-Dist: requests>=2.32.3
Requires-Dist: retry>=0.9.2
Requires-Dist: rpi-gpio>=0.7.1
